tests/__init__.py
tests/test_Jasper_db_postgres.py
tests/test_Jasper_webcrawler.py
tests/test_Jasper_webdriver.py
twJTools/Jasper_db_postgres.py
twJTools/Jasper_webcrawler.py
twJTools/Jasper_webdriver.py
twJTools/__init__.py
twJTools-0.1.2.1.dist-info/LICENSE
twJTools-0.1.2.1.dist-info/METADATA
twJTools-0.1.2.1.dist-info/WHEEL
twJTools-0.1.2.1.dist-info/top_level.txt
twJTools-0.1.2.1.dist-info/RECORD
