Metadata-Version: 2.1
Name: twJTools
Version: 0.1.2.1
Summary: A core utility library by Jasper
Home-page: https://github.com/tatsuno/twJTools
Author: Jasper
Author-email: tatsuno46@gmail.com
Classifier: Programming Language :: Python :: 3
Classifier: License :: OSI Approved :: MIT License
Classifier: Operating System :: OS Independent
Requires-Python: >=3.10
License-File: LICENSE
Requires-Dist: webdriver-manager >=4.0.1
Requires-Dist: selenium >=4.22.0
Requires-Dist: psycopg2-binary >=2.9.9
Requires-Dist: beautifulsoup4 >=4.12.3
